pyvyos/__init__.py
pyvyos/device.py
pyvyos-0.2.1.dist-info/METADATA
pyvyos-0.2.1.dist-info/WHEEL
pyvyos-0.2.1.dist-info/licenses/LICENSE
pyvyos-0.2.1.dist-info/RECORD
