Metadata-Version: 2.3
Name: pyvyos
Version: 0.2.1
Summary: Python SDK for interacting with VyOS API
Project-URL: Homepage, https://github.com/robertoberto/pyvyos
Project-URL: Issues, https://github.com/robertoberto/pyvyos/issues
Author-email: Roberto Berto <463349+robertoberto@users.noreply.github.com>
License-File: LICENSE
Classifier: License :: OSI Approved :: MIT License
Classifier: Operating System :: OS Independent
Classifier: Programming Language :: Python :: 3
Requires-Python: >=3.8
